{
    "tot": 1000,
    "success": 1010,
    "fail": 0,
    "icp_time": [],
    "kel_time": [],
    "icp_time_s": [],
    "kel_time_s": [],
    "rot_time_s": [],
    "1": [
        8050,
        8546,
        8032,
        8465,
        8514,
        8183,
        8113,
        8465,
        8303,
        8479,
        7937,
        8255,
        7476,
        7977,
        7836,
        8085,
        8072,
        7541,
        8046,
        7960,
        6960,
        7217,
        7234,
        7149,
        7357,
        7074,
        6637,
        6968,
        6895,
        7117,
        8320,
        8678,
        7900,
        8545,
        7834,
        7775,
        8717,
        8366,
        8366,
        8423,
        6969,
        7003,
        6942,
        6907,
        6863,
        7134,
        6224,
        7018,
        6981,
        6956,
        8243,
        8089,
        7845,
        7741,
        7875,
        8143,
        8428,
        8034,
        7993,
        7739,
        7156,
        7124,
        6966,
        7074,
        7254,
        6987,
        6991,
        6944,
        7370,
        7418,
        8442,
        8222,
        8028,
        7562,
        8038,
        8273,
        8024,
        7524,
        8303,
        7994,
        7368,
        7083,
        7188,
        7099,
        7377,
        7238,
        7336,
        7067,
        6903,
        6805,
        6680,
        6782,
        7138,
        6660,
        6457,
        6472,
        6774,
        6804,
        6572,
        6889,
        6719,
        6534,
        6402,
        5808,
        6383,
        6551,
        6409,
        6623,
        6448,
        6892,
        6837,
        7015,
        7104,
        6465,
        7081,
        6731,
        6843,
        7042,
        6976,
        7074,
        5910,
        6175,
        5939,
        6113,
        6256,
        6106,
        5975,
        6021,
        6235,
        6073,
        7911,
        7422,
        7586,
        7348,
        7493,
        7037,
        7307,
        7328,
        7556,
        7251,
        6147,
        6385,
        6022,
        6451,
        6391,
        6035,
        6303,
        6081,
        6375,
        6322,
        7750,
        7601,
        7499,
        7454,
        7326,
        7234,
        7386,
        7383,
        7525,
        7369,
        6801,
        7106,
        6883,
        6665,
        6930,
        7108,
        6904,
        7146,
        6928,
        7113,
        6436,
        6225,
        6025,
        5891,
        6016,
        5963,
        5866,
        6051,
        6011,
        5871,
        5801,
        5788,
        5034,
        5867,
        5805,
        5924,
        5831,
        6012,
        5561,
        5837,
        6175,
        6300,
        6547,
        6255,
        6322,
        6250,
        6467,
        5775,
        6346,
        6245,
        8116,
        7907,
        8243,
        8072,
        8204,
        8130,
        8214,
        7562,
        8346,
        8349,
        7747,
        8355,
        8035,
        8041,
        7663,
        8095,
        8087,
        8178,
        8353,
        8066,
        5924,
        5881,
        5999,
        5982,
        5938,
        6046,
        5508,
        5973,
        5785,
        6150,
        6119,
        6098,
        5583,
        6016,
        5704,
        6051,
        5458,
        5469,
        6096,
        5624,
        6548,
        5942,
        6297,
        6202,
        6559,
        5789,
        6194,
        6257,
        6269,
        6404,
        6430,
        6338,
        6371,
        6020,
        6239,
        5912,
        6378,
        5996,
        6146,
        6359,
        8196,
        7976,
        8398,
        8367,
        8436,
        8364,
        8275,
        8177,
        8466,
        8328,
        9741,
        10133,
        9973,
        10136,
        10087,
        9332,
        9817,
        9791,
        9994,
        10029,
        9756,
        9681,
        9737,
        9627,
        9862,
        9756,
        9737,
        9740,
        9756,
        9859,
        8384,
        8357,
        8269,
        8452,
        8290,
        8558,
        8291,
        8367,
        8242,
        7759,
        8750,
        8676,
        8605,
        8573,
        8617,
        8614,
        8704,
        8729,
        8686,
        8513,
        7012,
        7058,
        7235,
        7015,
        6884,
        7254,
        7417,
        7183,
        7247,
        7320,
        6917,
        6982,
        6810,
        7151,
        6982,
        6856,
        6813,
        6689,
        6877,
        7120,
        9180,
        9689,
        9250,
        9840,
        8924,
        9320,
        9605,
        9526,
        9694,
        9853,
        9536,
        9516,
        9643,
        9646,
        9545,
        9583,
        9373,
        9245,
        9693,
        9524,
        6967,
        7192,
        7008,
        6951,
        7191,
        7186,
        7097,
        6504,
        7120,
        6905,
        9419,
        9882,
        9712,
        9655,
        9725,
        9859,
        9630,
        9717,
        9304,
        9868,
        8929,
        9161,
        8507,
        8894,
        9374,
        9331,
        9025,
        9011,
        8842,
        9240,
        8412,
        8489,
        8014,
        8675,
        8270,
        8459,
        8277,
        8538,
        8031,
        8524,
        7349,
        7054,
        7295,
        7265,
        7186,
        7419,
        7071,
        7240,
        7242,
        7230,
        8963,
        8993,
        9000,
        8987,
        9355,
        9170,
        9086,
        9246,
        9361,
        9256,
        9633,
        9464,
        9402,
        9625,
        9681,
        9503,
        9756,
        9652,
        9717,
        9739,
        7394,
        7253,
        6973,
        7302,
        6823,
        7055,
        7255,
        6894,
        7227,
        6910,
        10054,
        10052,
        9975,
        9764,
        10125,
        9964,
        9620,
        10000,
        9837,
        9797,
        9596,
        9725,
        9605,
        9809,
        9222,
        9492,
        9352,
        9156,
        9599,
        9729,
        10020,
        10163,
        9649,
        10093,
        10278,
        10195,
        10037,
        10177,
        10078,
        10126,
        8915,
        9226,
        9065,
        9108,
        9211,
        8974,
        8702,
        9110,
        8896,
        8532,
        10751,
        10542,
        10316,
        10711,
        10537,
        10700,
        11110,
        10775,
        10749,
        10972,
        8873,
        8955,
        8788,
        8844,
        9086,
        8719,
        8993,
        8939,
        8916,
        8905,
        8254,
        8099,
        8317,
        8456,
        8336,
        8311,
        8212,
        8028,
        7888,
        8300,
        7765,
        7805,
        7616,
        7619,
        7923,
        7846,
        7997,
        7662,
        7538,
        7753,
        9009,
        9042,
        8914,
        9121,
        9282,
        9250,
        9153,
        8925,
        9077,
        8566,
        9133,
        9144,
        9218,
        8863,
        8755,
        9310,
        9133,
        9097,
        9018,
        9466,
        9286,
        9247,
        9242,
        9205,
        9194,
        9237,
        9107,
        9026,
        9742,
        9078,
        8264,
        8580,
        8094,
        8539,
        8358,
        8536,
        8320,
        8719,
        8503,
        8120,
        7422,
        7314,
        7396,
        7794,
        7705,
        7150,
        7422,
        7560,
        7362,
        7059,
        9901,
        10003,
        10312,
        10084,
        9922,
        9847,
        10120,
        9884,
        9786,
        9963,
        9608,
        9470,
        9752,
        9223,
        9626,
        9569,
        9447,
        9736,
        9420,
        9388,
        8662,
        8639,
        8872,
        8840,
        8410,
        8722,
        8901,
        8920,
        8812,
        8952,
        9581,
        9210,
        9402,
        9489,
        9329,
        9275,
        9410,
        9389,
        9683,
        9470,
        9307,
        9396,
        9664,
        9577,
        9514,
        9494,
        9607,
        9724,
        9578,
        9627,
        8935,
        9010,
        9213,
        8724,
        8955,
        8965,
        9100,
        8799,
        8789,
        9257,
        9766,
        9451,
        9914,
        10066,
        9349,
        9950,
        10294,
        9947,
        9624,
        9979,
        9574,
        9520,
        9453,
        9492,
        9721,
        9646,
        9763,
        9548,
        9204,
        9488,
        9709,
        9807,
        9076,
        9359,
        9536,
        9292,
        9662,
        9160,
        9266,
        9548,
        9465,
        9852,
        9623,
        9894,
        9293,
        9758,
        9312,
        9342,
        10121,
        9709,
        8558,
        8834,
        8701,
        9065,
        8846,
        8931,
        9026,
        8819,
        8779,
        8526,
        9545,
        9232,
        9259,
        8592,
        8797,
        9376,
        9101,
        9326,
        9452,
        9663,
        8871,
        8468,
        8462,
        8795,
        9099,
        8487,
        8670,
        8632,
        8336,
        8538,
        9468,
        9789,
        9578,
        9681,
        9304,
        9579,
        9726,
        9266,
        9566,
        8908,
        9488,
        9486,
        9730,
        9701,
        9612,
        8601,
        9857,
        9241,
        9237,
        9502,
        8381,
        8394,
        8295,
        7904,
        8397,
        8080,
        8190,
        8512,
        8517,
        8388,
        9075,
        9088,
        8581,
        8762,
        9172,
        9012,
        9059,
        8998,
        8928,
        8859,
        10235,
        9892,
        9924,
        10080,
        9928,
        10158,
        9635,
        9401,
        9821,
        10338,
        8951,
        9079,
        8421,
        8932,
        8812,
        8872,
        8936,
        9079,
        8867,
        8919,
        9271,
        9220,
        9419,
        8501,
        9326,
        9372,
        9180,
        9465,
        8892,
        9324,
        9714,
        9854,
        10023,
        10041,
        9897,
        9606,
        9919,
        9732,
        9797,
        9574,
        9506,
        9543,
        9881,
        9618,
        9123,
        9410,
        10010,
        9652,
        9698,
        9701,
        9546,
        9608,
        9878,
        9734,
        9633,
        9686,
        9623,
        9686,
        9492,
        9703,
        9686,
        9878,
        10003,
        9548,
        9493,
        10147,
        9932,
        10154,
        9894,
        9732,
        10154,
        9636,
        10087,
        9524,
        9634,
        9665,
        9532,
        9964,
        9579,
        9385,
        9928,
        9663,
        9682,
        9861,
        9717,
        9618,
        9990,
        9982,
        9744,
        9393,
        9428,
        10046,
        10210,
        10117,
        9655,
        10039,
        9648,
        9398,
        10041,
        9992,
        9609,
        9041,
        9224,
        9307,
        9332,
        9349,
        9142,
        9157,
        9007,
        8791,
        10243,
        10188,
        10147,
        10050,
        10338,
        10513,
        10533,
        10276,
        10071,
        10248,
        10991,
        11212,
        11101,
        11075,
        10901,
        11382,
        11092,
        10433,
        10804,
        11223,
        10675,
        10543,
        10525,
        10797,
        10807,
        10321,
        10648,
        10635,
        10723,
        10408,
        10553,
        10393,
        10292,
        10469,
        10439,
        10260,
        10470,
        9894,
        10487,
        10761,
        10185,
        10310,
        10376,
        10180,
        10277,
        10148,
        10166,
        9955,
        10341,
        10429,
        9531,
        9111,
        9320,
        8995,
        9359,
        9240,
        9274,
        9182,
        9526,
        9535,
        9871,
        9550,
        10088,
        9809,
        9514,
        9347,
        9628,
        9586,
        9633,
        9883,
        8787,
        8786,
        8679,
        8715,
        8830,
        8787,
        8632,
        8653,
        8704,
        8918,
        9727,
        9574,
        9683,
        9485,
        9617,
        9483,
        9356,
        9895,
        9253,
        9548,
        10561,
        9932,
        10584,
        10337,
        10434,
        10289,
        10714,
        10243,
        10200,
        10024,
        10978,
        10896,
        11057,
        10735,
        10867,
        10803,
        10836,
        11120,
        11249,
        10585,
        10018,
        9791,
        9613,
        10041,
        9409,
        9966,
        10012,
        9607,
        10006,
        9725,
        10142,
        10013,
        9944,
        9937,
        9675,
        10020,
        9264,
        9200,
        9204,
        9787,
        10577,
        10471,
        10848,
        10415,
        10871,
        10780,
        10757,
        10583,
        10531,
        10515,
        9609,
        9661,
        9267,
        9490,
        9528,
        9486,
        9689,
        9755,
        9588,
        9218,
        10109,
        10001,
        10133,
        10143,
        9921,
        10167,
        10326,
        10057,
        10035,
        10285,
        10495,
        10510,
        10766,
        11054,
        10778,
        10831,
        10804,
        10744,
        10517,
        10738
    ],
    "2": [
        0,
        0,
        0,
        0,
        0,
        0,
        0,
        0,
        0,
        0,
        0,
        0,
        0,
        0,
        0,
        0,
        0,
        0,
        0,
        0,
        0,
        0,
        0,
        0,
        0,
        0,
        0,
        0,
        0,
        0,
        0,
        0,
        0,
        0,
        0,
        0,
        0,
        0,
        0,
        0,
        0,
        0,
        0,
        0,
        0,
        0,
        0,
        0,
        0,
        0,
        0,
        0,
        0,
        0,
        0,
        0,
        0,
        0,
        0,
        0,
        0,
        0,
        0,
        0,
        0,
        0,
        0,
        2,
        0,
        1,
        0,
        0,
        0,
        0,
        0,
        0,
        0,
        0,
        0,
        0,
        0,
        0,
        0,
        0,
        0,
        0,
        0,
        0,
        0,
        0,
        0,
        0,
        0,
        0,
        0,
        0,
        0,
        0,
        0,
        0,
        0,
        0,
        0,
        0,
        0,
        0,
        0,
        0,
        0,
        0,
        0,
        0,
        0,
        0,
        0,
        0,
        0,
        0,
        0,
        0,
        0,
        0,
        0,
        0,
        0,
        0,
        0,
        0,
        0,
        0,
        0,
        0,
        0,
        0,
        0,
        0,
        0,
        0,
        0,
        0,
        0,
        0,
        0,
        0,
        0,
        0,
        0,
        0,
        0,
        0,
        0,
        0,
        0,
        0,
        0,
        0,
        0,
        0,
        0,
        0,
        0,
        0,
        0,
        0,
        0,
        0,
        0,
        0,
        0,
        0,
        0,
        0,
        0,
        0,
        0,
        0,
        0,
        0,
        0,
        0,
        0,
        0,
        0,
        0,
        0,
        0,
        0,
        0,
        0,
        0,
        0,
        0,
        0,
        0,
        0,
        0,
        0,
        0,
        0,
        0,
        0,
        0,
        0,
        0,
        0,
        0,
        0,
        0,
        0,
        0,
        0,
        0,
        0,
        0,
        0,
        0,
        0,
        0,
        0,
        0,
        0,
        0,
        0,
        0,
        0,
        0,
        0,
        0,
        0,
        0,
        0,
        0,
        0,
        0,
        0,
        0,
        0,
        0,
        0,
        0,
        0,
        0,
        0,
        0,
        0,
        0,
        0,
        0,
        0,
        0,
        0,
        0,
        0,
        0,
        0,
        0,
        0,
        0,
        0,
        0,
        0,
        0,
        0,
        0,
        0,
        0,
        0,
        0,
        0,
        0,
        0,
        0,
        0,
        1,
        0,
        0,
        0,
        0,
        0,
        0,
        0,
        0,
        0,
        0,
        0,
        0,
        0,
        0,
        0,
        0,
        0,
        0,
        0,
        0,
        0,
        0,
        0,
        0,
        0,
        0,
        0,
        0,
        0,
        0,
        0,
        0,
        0,
        0,
        0,
        0,
        0,
        0,
        0,
        0,
        0,
        0,
        0,
        0,
        0,
        0,
        0,
        0,
        0,
        0,
        0,
        0,
        0,
        0,
        0,
        0,
        0,
        0,
        0,
        0,
        0,
        0,
        0,
        0,
        0,
        0,
        0,
        0,
        0,
        0,
        0,
        0,
        0,
        0,
        0,
        0,
        0,
        0,
        0,
        0,
        0,
        0,
        0,
        0,
        0,
        0,
        0,
        0,
        0,
        0,
        0,
        0,
        0,
        0,
        0,
        0,
        0,
        0,
        0,
        0,
        0,
        0,
        0,
        0,
        0,
        0,
        0,
        0,
        0,
        0,
        0,
        0,
        0,
        0,
        0,
        0,
        0,
        0,
        0,
        0,
        0,
        0,
        0,
        0,
        0,
        0,
        0,
        0,
        0,
        0,
        0,
        0,
        0,
        0,
        0,
        0,
        0,
        0,
        0,
        0,
        0,
        0,
        0,
        0,
        0,
        0,
        0,
        0,
        0,
        0,
        0,
        0,
        0,
        0,
        0,
        0,
        0,
        0,
        0,
        0,
        0,
        0,
        0,
        0,
        0,
        0,
        0,
        0,
        0,
        0,
        0,
        0,
        0,
        0,
        0,
        0,
        0,
        0,
        0,
        0,
        0,
        0,
        0,
        0,
        0,
        0,
        0,
        0,
        0,
        0,
        0,
        0,
        0,
        0,
        0,
        0,
        0,
        0,
        0,
        0,
        0,
        0,
        0,
        0,
        0,
        0,
        0,
        0,
        0,
        0,
        0,
        0,
        0,
        0,
        0,
        0,
        0,
        0,
        0,
        0,
        0,
        0,
        0,
        0,
        0,
        0,
        0,
        0,
        0,
        0,
        0,
        0,
        0,
        0,
        0,
        0,
        0,
        0,
        0,
        0,
        0,
        0,
        0,
        0,
        0,
        0,
        0,
        0,
        0,
        0,
        0,
        0,
        0,
        0,
        0,
        0,
        0,
        0,
        0,
        0,
        0,
        0,
        0,
        0,
        0,
        0,
        0,
        0,
        0,
        0,
        0,
        0,
        0,
        0,
        0,
        0,
        0,
        0,
        0,
        0,
        0,
        0,
        0,
        0,
        0,
        0,
        0,
        0,
        0,
        0,
        0,
        0,
        0,
        0,
        0,
        0,
        0,
        0,
        0,
        1,
        0,
        0,
        0,
        0,
        0,
        1,
        0,
        0,
        0,
        0,
        0,
        0,
        0,
        0,
        0,
        0,
        0,
        0,
        0,
        0,
        0,
        0,
        0,
        0,
        0,
        0,
        0,
        0,
        0,
        0,
        0,
        0,
        0,
        0,
        0,
        0,
        0,
        0,
        0,
        0,
        0,
        0,
        0,
        0,
        0,
        0,
        0,
        0,
        0,
        0,
        0,
        0,
        0,
        0,
        0,
        0,
        0,
        0,
        0,
        0,
        0,
        0,
        0,
        0,
        0,
        0,
        0,
        0,
        0,
        0,
        0,
        0,
        0,
        0,
        0,
        0,
        0,
        0,
        0,
        0,
        0,
        0,
        0,
        0,
        0,
        0,
        0,
        0,
        0,
        0,
        0,
        0,
        0,
        0,
        0,
        0,
        0,
        0,
        0,
        0,
        0,
        0,
        0,
        0,
        0,
        0,
        0,
        0,
        0,
        0,
        0,
        0,
        0,
        0,
        0,
        0,
        0,
        0,
        0,
        0,
        0,
        0,
        0,
        0,
        0,
        0,
        0,
        0,
        0,
        0,
        0,
        0,
        0,
        0,
        0,
        0,
        0,
        0,
        0,
        0,
        0,
        0,
        0,
        0,
        0,
        0,
        0,
        0,
        0,
        0,
        0,
        0,
        0,
        0,
        0,
        0,
        0,
        0,
        0,
        0,
        0,
        0,
        0,
        0,
        0,
        0,
        0,
        0,
        0,
        0,
        0,
        0,
        0,
        0,
        0,
        0,
        0,
        0,
        0,
        0,
        0,
        0,
        0,
        0,
        0,
        0,
        0,
        0,
        0,
        0,
        0,
        0,
        0,
        0,
        0,
        0,
        0,
        0,
        0,
        0,
        0,
        0,
        0,
        1,
        0,
        0,
        0,
        0,
        0,
        0,
        0,
        2,
        0,
        0,
        0,
        0,
        0,
        0,
        0,
        0,
        0,
        0,
        0,
        0,
        0,
        0,
        0,
        0,
        0,
        0,
        0,
        0,
        0,
        0,
        0,
        0,
        0,
        0,
        0,
        0,
        0,
        0,
        0,
        0,
        0,
        0,
        0,
        0,
        0,
        0,
        0,
        0,
        0,
        0,
        0,
        0,
        0,
        0,
        0,
        0,
        0,
        0,
        0,
        0,
        0,
        0,
        2,
        0,
        2,
        0,
        0,
        0,
        0,
        0,
        0,
        0,
        0,
        0,
        0,
        0,
        0,
        0,
        0,
        0,
        0,
        0,
        0,
        0,
        0,
        0,
        0,
        0,
        0,
        0,
        0,
        0,
        0,
        0,
        0,
        0,
        0,
        0,
        0,
        0,
        0,
        0,
        0,
        0,
        0,
        0,
        0,
        0,
        0,
        0,
        0,
        0,
        0,
        0,
        0,
        2,
        0,
        0,
        3,
        0,
        5,
        2,
        0,
        0,
        0,
        0,
        0,
        0,
        0,
        0,
        0,
        0,
        0,
        0,
        0,
        0,
        0,
        0,
        0,
        0,
        0,
        0,
        0,
        0,
        0,
        0,
        0,
        0,
        0,
        0,
        0,
        0,
        0,
        0,
        0,
        0,
        0,
        0,
        0,
        0,
        0,
        0,
        0,
        0,
        0,
        0,
        0,
        0,
        0,
        0,
        0,
        0,
        0,
        0,
        0,
        0,
        0,
        0,
        0,
        0,
        0,
        0,
        0,
        0,
        0,
        0,
        0,
        0,
        0,
        0,
        0,
        0,
        0,
        0,
        0,
        0,
        0,
        0,
        0,
        0,
        0,
        0,
        0,
        0,
        0,
        0,
        0,
        0,
        0,
        0,
        0,
        0,
        0,
        0,
        0,
        0,
        0,
        0,
        0,
        0,
        0,
        0,
        0,
        0,
        0,
        0,
        0,
        0,
        0,
        0,
        0,
        0
    ],
    "3": [
        2289,
        1593,
        3652,
        3165,
        3144,
        3115,
        3037,
        3170,
        2799,
        3674,
        1190,
        3150,
        3762,
        3548,
        2883,
        3239,
        2943,
        1017,
        2878,
        2626,
        952,
        2056,
        2686,
        576,
        1364,
        2861,
        905,
        769,
        1190,
        1756,
        1463,
        1815,
        1238,
        1838,
        673,
        673,
        1037,
        1515,
        1181,
        1060,
        1332,
        2416,
        2843,
        2727,
        2133,
        2729,
        607,
        3163,
        1230,
        2244,
        848,
        715,
        1436,
        1612,
        1576,
        553,
        1161,
        1065,
        897,
        1376,
        539,
        2411,
        698,
        544,
        2822,
        2787,
        715,
        2965,
        2581,
        2497,
        721,
        1590,
        858,
        1347,
        989,
        1272,
        1130,
        977,
        1609,
        1481,
        632,
        1319,
        1533,
        1090,
        829,
        698,
        1410,
        1157,
        1073,
        688,
        890,
        1422,
        1209,
        665,
        827,
        1365,
        812,
        1128,
        586,
        967,
        1041,
        1047,
        1417,
        1171,
        1385,
        892,
        1290,
        750,
        854,
        653,
        1056,
        1515,
        858,
        730,
        696,
        956,
        1506,
        1280,
        975,
        1316,
        770,
        679,
        1259,
        657,
        1037,
        954,
        1323,
        814,
        1399,
        1220,
        814,
        734,
        1432,
        1368,
        656,
        1164,
        911,
        1686,
        1248,
        1545,
        1214,
        772,
        965,
        1361,
        752,
        1442,
        622,
        607,
        1079,
        1056,
        1613,
        705,
        957,
        919,
        1331,
        1482,
        1312,
        991,
        663,
        922,
        740,
        1063,
        1371,
        523,
        600,
        1053,
        1433,
        886,
        1293,
        1288,
        544,
        1047,
        1391,
        1161,
        712,
        506,
        1239,
        699,
        1331,
        982,
        1025,
        809,
        1107,
        609,
        1266,
        1293,
        794,
        950,
        1215,
        545,
        788,
        1194,
        641,
        1225,
        1014,
        542,
        1257,
        869,
        1338,
        1057,
        791,
        1638,
        1002,
        792,
        1205,
        1355,
        1032,
        1358,
        1660,
        1153,
        1715,
        734,
        836,
        1519,
        991,
        1359,
        1365,
        1580,
        1141,
        1776,
        1393,
        1180,
        1073,
        571,
        572,
        845,
        942,
        855,
        973,
        1265,
        551,
        993,
        765,
        737,
        1222,
        926,
        1282,
        1241,
        637,
        1080,
        1169,
        597,
        1245,
        792,
        855,
        485,
        1391,
        1375,
        1004,
        918,
        1053,
        1415,
        988,
        677,
        565,
        787,
        812,
        1325,
        1236,
        1203,
        1095,
        1617,
        1022,
        1579,
        1314,
        906,
        1752,
        1271,
        712,
        1772,
        2190,
        1046,
        998,
        1178,
        1429,
        828,
        1930,
        2239,
        1809,
        1446,
        1758,
        1666,
        1101,
        1371,
        827,
        1483,
        955,
        1746,
        1535,
        1211,
        820,
        1656,
        1586,
        932,
        903,
        840,
        1759,
        1340,
        1738,
        1339,
        1481,
        1290,
        1027,
        1078,
        801,
        720,
        1025,
        1391,
        1155,
        1016,
        688,
        1473,
        1078,
        1298,
        892,
        860,
        693,
        1622,
        1353,
        1155,
        738,
        1138,
        1553,
        992,
        843,
        864,
        1231,
        980,
        737,
        1508,
        934,
        1717,
        956,
        1696,
        1165,
        1780,
        1473,
        1260,
        1408,
        1975,
        841,
        1936,
        1995,
        1431,
        896,
        1786,
        1335,
        1192,
        1216,
        1746,
        1258,
        1328,
        712,
        1104,
        1418,
        755,
        1429,
        718,
        683,
        1071,
        972,
        1172,
        888,
        974,
        1468,
        1555,
        1666,
        2060,
        1943,
        1489,
        1504,
        1644,
        1664,
        1109,
        1239,
        1839,
        972,
        1493,
        1273,
        864,
        718,
        1082,
        1523,
        1044,
        1360,
        816,
        1063,
        1102,
        1438,
        1344,
        1375,
        958,
        659,
        1330,
        1137,
        712,
        849,
        838,
        1629,
        1652,
        1039,
        1307,
        1477,
        1372,
        967,
        1830,
        768,
        1863,
        1345,
        1163,
        867,
        1792,
        1118,
        1175,
        1688,
        1812,
        1653,
        825,
        1100,
        1268,
        917,
        1567,
        1059,
        1584,
        1313,
        1362,
        970,
        577,
        1200,
        657,
        1398,
        1830,
        1436,
        1005,
        2027,
        1024,
        1228,
        1821,
        1275,
        1924,
        1000,
        1530,
        1727,
        1882,
        888,
        1255,
        1100,
        2073,
        1825,
        1461,
        2026,
        1537,
        1181,
        1054,
        1560,
        812,
        2003,
        1172,
        946,
        1287,
        1189,
        1689,
        1757,
        1423,
        1989,
        1139,
        2210,
        813,
        958,
        1509,
        992,
        1795,
        2062,
        1030,
        1409,
        1494,
        1934,
        1596,
        1242,
        1119,
        1245,
        1311,
        1008,
        896,
        942,
        1471,
        1293,
        882,
        682,
        691,
        950,
        1038,
        1181,
        1400,
        1473,
        1326,
        750,
        927,
        1388,
        673,
        1380,
        1102,
        714,
        923,
        730,
        1215,
        1583,
        792,
        1292,
        1140,
        965,
        1978,
        1313,
        2149,
        1585,
        2086,
        884,
        1257,
        1957,
        1222,
        861,
        1093,
        1686,
        1686,
        1553,
        987,
        1125,
        1514,
        874,
        1055,
        1671,
        1889,
        1197,
        1247,
        1588,
        1449,
        1185,
        918,
        1867,
        771,
        1168,
        694,
        1679,
        936,
        1325,
        828,
        1030,
        1646,
        1004,
        1458,
        1761,
        1768,
        798,
        1374,
        1256,
        1217,
        1471,
        1020,
        995,
        658,
        1470,
        1186,
        883,
        1843,
        1467,
        2143,
        2249,
        1914,
        1418,
        1588,
        1739,
        1069,
        1465,
        803,
        1688,
        1188,
        1438,
        905,
        1950,
        2016,
        1574,
        815,
        848,
        1194,
        1829,
        1164,
        1820,
        1596,
        1214,
        1018,
        984,
        1712,
        1345,
        586,
        1073,
        1377,
        771,
        1847,
        1244,
        1612,
        1900,
        695,
        1778,
        1348,
        854,
        1194,
        1076,
        1586,
        1002,
        1566,
        842,
        1095,
        1769,
        1426,
        1418,
        1206,
        1134,
        1778,
        855,
        859,
        716,
        1453,
        1632,
        1206,
        1977,
        670,
        1950,
        1181,
        988,
        1061,
        990,
        1265,
        1432,
        1598,
        1347,
        1139,
        943,
        1821,
        852,
        1804,
        1232,
        937,
        1772,
        1891,
        1084,
        1990,
        1513,
        1509,
        1456,
        998,
        1961,
        1706,
        1315,
        1643,
        1427,
        1910,
        992,
        2181,
        1442,
        1124,
        787,
        1310,
        1638,
        637,
        1159,
        1544,
        941,
        778,
        1852,
        1740,
        1440,
        1080,
        865,
        936,
        1777,
        1890,
        1590,
        1268,
        1061,
        1528,
        842,
        1046,
        1771,
        1575,
        1302,
        1144,
        1155,
        1613,
        890,
        1659,
        1709,
        1100,
        1703,
        665,
        1286,
        2014,
        1124,
        824,
        1953,
        1287,
        1635,
        734,
        1829,
        1080,
        1286,
        948,
        1643,
        1273,
        847,
        1861,
        872,
        995,
        920,
        1766,
        1744,
        1225,
        1379,
        853,
        1257,
        1587,
        1617,
        1985,
        1332,
        800,
        1829,
        1036,
        1203,
        1885,
        855,
        1111,
        1994,
        1523,
        1228,
        1220,
        1259,
        1663,
        1932,
        953,
        887,
        1800,
        822,
        1276,
        1773,
        1811,
        1115,
        1269,
        1482,
        820,
        1448,
        1092,
        1393,
        1777,
        894,
        1158,
        1973,
        843,
        1732,
        1420,
        1767,
        993,
        1578,
        1339,
        1956,
        897,
        938,
        679,
        1479,
        1099,
        1752,
        1309,
        796,
        1872,
        1625,
        1389,
        1370,
        875,
        1580,
        1836,
        886,
        1133,
        1938,
        1105,
        960,
        950,
        1178,
        1367,
        1413,
        1727,
        1616,
        2049,
        912,
        1294,
        1729,
        1520,
        1254,
        1061,
        1049,
        998,
        897,
        1160,
        1675,
        825,
        863,
        2014,
        1174,
        1397,
        1850,
        1339,
        1701,
        1084,
        969,
        1842,
        1544,
        1953,
        920,
        1791,
        1197,
        2060,
        1151,
        1368,
        1331,
        2017,
        2289,
        1305,
        1559,
        1487,
        2374,
        1046,
        1090,
        2048,
        957,
        1827,
        1536,
        1428,
        797,
        1203,
        1356,
        1625,
        1181,
        1988,
        1601,
        1081,
        813,
        1753,
        1932,
        1860,
        925,
        1180,
        2067,
        1498,
        1273,
        1730,
        933,
        2000,
        1438,
        1773,
        1200,
        1975,
        1476,
        908,
        1966,
        1074,
        1064,
        1282,
        1701,
        854,
        1351,
        1630,
        713,
        1929,
        1467,
        2073,
        2018,
        1582,
        1263,
        1477,
        1007,
        868,
        1196,
        1789,
        1469,
        1318,
        707,
        973,
        883,
        1168,
        1396,
        1599,
        703,
        1203,
        1154,
        876,
        1984,
        1685,
        1403,
        1332,
        1068,
        834,
        1936,
        1775,
        1541,
        1661,
        1409,
        965,
        788,
        1942,
        1401,
        1073,
        1111,
        1929,
        1317,
        2189,
        1778,
        1013,
        893,
        1919,
        1317,
        1543,
        1134,
        2209,
        1231,
        1416,
        1089,
        885,
        1571,
        2049,
        1779,
        727,
        1379,
        1982,
        1616,
        1770,
        1823,
        1121,
        1063,
        1277,
        990,
        1518,
        1564,
        674,
        1616,
        950,
        864,
        1050,
        941,
        731,
        1570,
        696,
        1253,
        1372,
        2040,
        1090,
        1692,
        1664,
        756,
        857,
        1157,
        2097,
        1339,
        1618,
        1183,
        978,
        1412,
        2059,
        1224,
        1853,
        1639,
        1898,
        2153,
        1047,
        1713,
        1112,
        980,
        1996,
        2212,
        1157,
        1266,
        1566,
        1744,
        913,
        1906,
        1140,
        1545,
        992,
        800,
        841,
        1214,
        1881,
        1245,
        1611,
        863,
        1669,
        1075,
        1283,
        985,
        1216,
        1635,
        2012,
        1499,
        1895,
        1520,
        1742,
        2110,
        1074,
        1984,
        1548,
        1646,
        1202,
        941,
        962
    ],
    "4": [
        0,
        0,
        0,
        0,
        0,
        0,
        0,
        0,
        0,
        0,
        0,
        0,
        0,
        0,
        0,
        0,
        0,
        0,
        0,
        0,
        0,
        0,
        0,
        0,
        0,
        0,
        0,
        0,
        0,
        0,
        0,
        0,
        0,
        0,
        0,
        0,
        0,
        0,
        0,
        0,
        0,
        0,
        0,
        0,
        0,
        0,
        0,
        0,
        0,
        0,
        0,
        0,
        0,
        0,
        0,
        0,
        0,
        0,
        0,
        0,
        0,
        0,
        0,
        0,
        0,
        0,
        0,
        0,
        0,
        0,
        0,
        0,
        0,
        0,
        0,
        0,
        0,
        0,
        0,
        0,
        0,
        0,
        0,
        0,
        0,
        0,
        0,
        0,
        0,
        0,
        0,
        0,
        0,
        0,
        0,
        0,
        0,
        0,
        0,
        0,
        0,
        0,
        0,
        0,
        0,
        0,
        0,
        0,
        0,
        0,
        0,
        0,
        0,
        0,
        0,
        0,
        0,
        0,
        0,
        0,
        0,
        0,
        0,
        0,
        0,
        0,
        0,
        0,
        0,
        0,
        0,
        0,
        0,
        0,
        0,
        0,
        0,
        0,
        0,
        0,
        0,
        0,
        0,
        0,
        0,
        0,
        0,
        0,
        0,
        0,
        0,
        0,
        0,
        0,
        0,
        0,
        0,
        0,
        0,
        0,
        0,
        0,
        0,
        0,
        0,
        0,
        0,
        0,
        0,
        0,
        0,
        0,
        0,
        0,
        0,
        0,
        0,
        0,
        0,
        0,
        0,
        0,
        0,
        0,
        0,
        0,
        0,
        0,
        0,
        0,
        0,
        0,
        0,
        0,
        0,
        0,
        0,
        0,
        0,
        0,
        0,
        0,
        0,
        0,
        0,
        0,
        0,
        0,
        0,
        0,
        0,
        0,
        0,
        0,
        0,
        0,
        0,
        0,
        0,
        0,
        0,
        0,
        0,
        0,
        0,
        0,
        0,
        0,
        0,
        0,
        0,
        0,
        0,
        0,
        0,
        0,
        0,
        0,
        0,
        0,
        0,
        0,
        0,
        0,
        0,
        0,
        0,
        0,
        0,
        0,
        0,
        0,
        0,
        0,
        0,
        0,
        0,
        0,
        0,
        0,
        0,
        0,
        0,
        0,
        0,
        0,
        0,
        0,
        0,
        0,
        0,
        0,
        0,
        0,
        0,
        0,
        0,
        0,
        0,
        0,
        0,
        0,
        0,
        0,
        0,
        0,
        0,
        0,
        0,
        0,
        0,
        0,
        0,
        0,
        0,
        0,
        0,
        0,
        0,
        0,
        0,
        0,
        0,
        0,
        0,
        0,
        0,
        0,
        0,
        0,
        0,
        0,
        0,
        0,
        0,
        0,
        0,
        0,
        0,
        0,
        0,
        0,
        0,
        0,
        0,
        0,
        0,
        0,
        0,
        0,
        0,
        0,
        0,
        0,
        0,
        0,
        0,
        0,
        0,
        0,
        0,
        0,
        0,
        0,
        0,
        0,
        0,
        0,
        0,
        0,
        0,
        0,
        0,
        0,
        0,
        0,
        0,
        0,
        0,
        0,
        0,
        0,
        0,
        0,
        0,
        0,
        0,
        0,
        0,
        0,
        0,
        0,
        0,
        0,
        0,
        0,
        0,
        0,
        0,
        0,
        0,
        0,
        0,
        0,
        0,
        0,
        0,
        0,
        0,
        0,
        0,
        0,
        0,
        0,
        0,
        0,
        0,
        0,
        0,
        0,
        0,
        0,
        0,
        0,
        0,
        0,
        0,
        0,
        0,
        0,
        0,
        0,
        0,
        0,
        0,
        0,
        0,
        0,
        0,
        0,
        0,
        0,
        0,
        0,
        0,
        0,
        0,
        0,
        0,
        0,
        0,
        0,
        0,
        0,
        0,
        0,
        0,
        0,
        0,
        0,
        0,
        0,
        0,
        0,
        0,
        0,
        0,
        0,
        0,
        0,
        0,
        0,
        0,
        0,
        0,
        0,
        0,
        0,
        0,
        0,
        0,
        0,
        0,
        0,
        0,
        0,
        0,
        0,
        0,
        0,
        0,
        0,
        0,
        0,
        0,
        0,
        0,
        0,
        0,
        0,
        0,
        0,
        0,
        0,
        0,
        0,
        0,
        0,
        0,
        0,
        0,
        0,
        0,
        0,
        0,
        0,
        0,
        0,
        0,
        0,
        0,
        0,
        0,
        0,
        0,
        0,
        0,
        0,
        0,
        0,
        0,
        0,
        0,
        0,
        0,
        0,
        0,
        0,
        0,
        0,
        0,
        0,
        0,
        0,
        0,
        0,
        0,
        0,
        0,
        0,
        0,
        0,
        0,
        0,
        0,
        0,
        0,
        0,
        0,
        0,
        0,
        0,
        0,
        0,
        0,
        0,
        0,
        0,
        0,
        0,
        0,
        0,
        0,
        0,
        0,
        0,
        0,
        0,
        0,
        0,
        0,
        0,
        0,
        0,
        0,
        0,
        0,
        0,
        0,
        0,
        0,
        0,
        0,
        0,
        0,
        0,
        0,
        0,
        0,
        0,
        0,
        0,
        0,
        0,
        0,
        0,
        0,
        0,
        0,
        0,
        0,
        0,
        0,
        0,
        0,
        0,
        0,
        0,
        0,
        0,
        0,
        0,
        0,
        0,
        0,
        0,
        0,
        0,
        0,
        0,
        0,
        0,
        0,
        0,
        0,
        0,
        0,
        0,
        0,
        0,
        0,
        0,
        0,
        0,
        0,
        0,
        0,
        0,
        0,
        0,
        0,
        0,
        0,
        0,
        0,
        0,
        0,
        0,
        0,
        0,
        0,
        0,
        0,
        0,
        0,
        0,
        0,
        0,
        0,
        0,
        0,
        0,
        0,
        0,
        0,
        0,
        0,
        0,
        0,
        0,
        0,
        0,
        0,
        0,
        0,
        0,
        0,
        0,
        0,
        0,
        0,
        0,
        0,
        0,
        0,
        0,
        0,
        0,
        0,
        0,
        0,
        0,
        0,
        0,
        0,
        0,
        0,
        0,
        0,
        0,
        0,
        0,
        0,
        0,
        0,
        0,
        0,
        0,
        0,
        0,
        0,
        0,
        0,
        0,
        0,
        0,
        0,
        0,
        0,
        0,
        0,
        0,
        0,
        0,
        0,
        0,
        0,
        0,
        0,
        0,
        0,
        0,
        0,
        0,
        0,
        0,
        0,
        0,
        0,
        0,
        0,
        0,
        0,
        0,
        0,
        0,
        0,
        0,
        0,
        0,
        0,
        0,
        0,
        0,
        0,
        0,
        0,
        0,
        0,
        0,
        0,
        0,
        0,
        0,
        0,
        0,
        0,
        0,
        0,
        0,
        0,
        0,
        0,
        0,
        0,
        0,
        0,
        0,
        0,
        0,
        0,
        0,
        0,
        0,
        0,
        0,
        0,
        0,
        0,
        0,
        0,
        0,
        0,
        0,
        0,
        0,
        0,
        0,
        0,
        0,
        0,
        0,
        0,
        0,
        0,
        0,
        0,
        0,
        0,
        0,
        0,
        0,
        0,
        0,
        0,
        0,
        0,
        0,
        0,
        0,
        0,
        0,
        0,
        0,
        0,
        0,
        0,
        0,
        0,
        0,
        0,
        0,
        0,
        0,
        0,
        0,
        0,
        0,
        0,
        0,
        0,
        0,
        0,
        0,
        0,
        0,
        0,
        0,
        0,
        0,
        0,
        0,
        0,
        0,
        0,
        0,
        0,
        0,
        0,
        0,
        0,
        0,
        0,
        0,
        0,
        0,
        0,
        0,
        0,
        0,
        0,
        0,
        0,
        0,
        0,
        0,
        0,
        0,
        0,
        0,
        0,
        0,
        0,
        0,
        0,
        0,
        0,
        0,
        0,
        0,
        0,
        0,
        0,
        0,
        0,
        0,
        0,
        0,
        0,
        0,
        0,
        0,
        0,
        0,
        0,
        0,
        0,
        0,
        0,
        0,
        0,
        0,
        0,
        0,
        0,
        0,
        0,
        0,
        0,
        0,
        0,
        0,
        0,
        0,
        0,
        0,
        0,
        0,
        0,
        0,
        0,
        0,
        0,
        0,
        0,
        0,
        0,
        0,
        0,
        0,
        0,
        0,
        0,
        0,
        0,
        0,
        0,
        0,
        0,
        0,
        0,
        0,
        0,
        0,
        0,
        0,
        0,
        0,
        0,
        0,
        0,
        0,
        0,
        0,
        0,
        0,
        0,
        0,
        0,
        0,
        0,
        0,
        0,
        0,
        0,
        0,
        0,
        0,
        0,
        0,
        0,
        0,
        0,
        0,
        0,
        0,
        0,
        0,
        0,
        0,
        0,
        0,
        0,
        0,
        0,
        0,
        0,
        0,
        0,
        0,
        0,
        0,
        0,
        0,
        0,
        0,
        0,
        0,
        0,
        0,
        0,
        0,
        0,
        0,
        0,
        0,
        0,
        0,
        0,
        0
    ],
    "5": [
        0,
        0,
        0,
        0,
        0,
        0,
        0,
        0,
        0,
        0,
        0,
        0,
        0,
        0,
        0,
        0,
        0,
        0,
        0,
        0,
        0,
        0,
        0,
        0,
        0,
        0,
        0,
        0,
        0,
        0,
        0,
        0,
        0,
        0,
        0,
        0,
        0,
        0,
        0,
        0,
        0,
        0,
        0,
        0,
        0,
        0,
        0,
        0,
        0,
        0,
        0,
        0,
        0,
        0,
        9,
        0,
        0,
        0,
        0,
        0,
        0,
        0,
        0,
        0,
        0,
        0,
        0,
        0,
        0,
        0,
        0,
        0,
        0,
        0,
        0,
        0,
        0,
        0,
        0,
        0,
        0,
        0,
        0,
        0,
        0,
        0,
        0,
        0,
        0,
        0,
        0,
        0,
        0,
        0,
        0,
        0,
        0,
        0,
        0,
        0,
        0,
        0,
        0,
        0,
        0,
        0,
        0,
        0,
        0,
        0,
        0,
        0,
        0,
        0,
        0,
        0,
        0,
        0,
        0,
        0,
        0,
        0,
        0,
        0,
        0,
        0,
        0,
        0,
        0,
        0,
        0,
        0,
        0,
        0,
        0,
        0,
        0,
        0,
        0,
        0,
        0,
        0,
        0,
        0,
        0,
        0,
        0,
        0,
        0,
        0,
        0,
        0,
        0,
        0,
        0,
        0,
        0,
        0,
        0,
        0,
        0,
        0,
        0,
        0,
        0,
        0,
        0,
        0,
        0,
        0,
        0,
        0,
        0,
        0,
        0,
        0,
        0,
        0,
        0,
        0,
        0,
        0,
        0,
        0,
        0,
        0,
        0,
        0,
        0,
        0,
        0,
        0,
        0,
        0,
        0,
        0,
        0,
        0,
        0,
        0,
        0,
        0,
        0,
        0,
        0,
        0,
        0,
        0,
        0,
        0,
        0,
        0,
        0,
        0,
        0,
        0,
        0,
        0,
        0,
        0,
        0,
        0,
        0,
        0,
        0,
        0,
        0,
        0,
        0,
        0,
        0,
        0,
        0,
        0,
        0,
        0,
        0,
        0,
        0,
        0,
        0,
        0,
        0,
        0,
        0,
        0,
        0,
        0,
        0,
        0,
        0,
        0,
        0,
        0,
        0,
        0,
        0,
        0,
        0,
        0,
        0,
        0,
        0,
        0,
        0,
        0,
        0,
        0,
        0,
        0,
        0,
        0,
        0,
        0,
        0,
        0,
        0,
        0,
        0,
        0,
        0,
        0,
        0,
        0,
        0,
        0,
        0,
        0,
        0,
        0,
        0,
        0,
        0,
        0,
        0,
        0,
        0,
        0,
        0,
        0,
        0,
        0,
        0,
        0,
        0,
        0,
        0,
        0,
        0,
        0,
        0,
        0,
        0,
        0,
        0,
        0,
        0,
        0,
        0,
        0,
        0,
        0,
        0,
        0,
        0,
        0,
        0,
        0,
        0,
        0,
        0,
        0,
        0,
        6,
        0,
        0,
        0,
        0,
        0,
        0,
        0,
        0,
        0,
        0,
        0,
        0,
        0,
        0,
        0,
        0,
        0,
        0,
        0,
        0,
        0,
        0,
        0,
        0,
        0,
        0,
        0,
        0,
        0,
        0,
        0,
        0,
        0,
        0,
        0,
        0,
        0,
        0,
        0,
        0,
        0,
        0,
        0,
        0,
        0,
        0,
        0,
        0,
        0,
        0,
        0,
        0,
        0,
        0,
        0,
        0,
        0,
        0,
        0,
        0,
        0,
        0,
        0,
        0,
        0,
        0,
        0,
        0,
        0,
        0,
        0,
        0,
        0,
        0,
        0,
        0,
        0,
        0,
        0,
        0,
        0,
        0,
        0,
        0,
        0,
        0,
        0,
        0,
        0,
        0,
        0,
        0,
        0,
        0,
        0,
        0,
        0,
        0,
        0,
        0,
        0,
        0,
        0,
        0,
        0,
        0,
        0,
        0,
        0,
        0,
        0,
        0,
        0,
        0,
        0,
        0,
        0,
        0,
        0,
        0,
        0,
        0,
        0,
        5,
        0,
        0,
        0,
        0,
        0,
        0,
        0,
        0,
        0,
        0,
        0,
        0,
        0,
        0,
        0,
        0,
        0,
        0,
        0,
        0,
        0,
        0,
        0,
        0,
        0,
        0,
        0,
        0,
        0,
        0,
        0,
        0,
        0,
        0,
        0,
        0,
        0,
        0,
        0,
        0,
        0,
        0,
        0,
        0,
        0,
        0,
        0,
        0,
        0,
        0,
        0,
        0,
        0,
        0,
        0,
        0,
        0,
        0,
        0,
        0,
        0,
        0,
        0,
        0,
        0,
        0,
        0,
        0,
        0,
        0,
        0,
        0,
        0,
        0,
        0,
        0,
        0,
        0,
        0,
        0,
        0,
        0,
        0,
        0,
        0,
        0,
        0,
        0,
        0,
        0,
        0,
        0,
        0,
        0,
        0,
        0,
        0,
        0,
        0,
        0,
        0,
        0,
        0,
        0,
        0,
        0,
        0,
        0,
        0,
        0,
        0,
        0,
        0,
        0,
        0,
        0,
        0,
        0,
        0,
        8,
        0,
        0,
        0,
        0,
        0,
        0,
        0,
        0,
        0,
        0,
        0,
        0,
        0,
        0,
        0,
        0,
        0,
        0,
        0,
        0,
        0,
        0,
        0,
        0,
        0,
        0,
        0,
        0,
        0,
        0,
        0,
        0,
        0,
        0,
        0,
        0,
        0,
        0,
        0,
        1,
        0,
        0,
        0,
        0,
        8,
        0,
        0,
        0,
        0,
        0,
        0,
        0,
        0,
        0,
        0,
        0,
        0,
        0,
        0,
        0,
        0,
        0,
        0,
        0,
        0,
        0,
        0,
        0,
        0,
        0,
        0,
        0,
        0,
        0,
        0,
        0,
        0,
        0,
        0,
        0,
        0,
        0,
        0,
        0,
        0,
        0,
        0,
        0,
        0,
        0,
        0,
        0,
        0,
        0,
        0,
        14,
        0,
        0,
        0,
        0,
        0,
        0,
        0,
        0,
        0,
        0,
        0,
        0,
        0,
        0,
        0,
        0,
        0,
        0,
        0,
        0,
        0,
        0,
        0,
        0,
        0,
        0,
        0,
        0,
        0,
        0,
        0,
        0,
        0,
        0,
        0,
        0,
        0,
        0,
        0,
        0,
        0,
        0,
        0,
        0,
        0,
        0,
        0,
        0,
        0,
        0,
        0,
        0,
        0,
        0,
        0,
        0,
        0,
        0,
        0,
        0,
        0,
        0,
        0,
        0,
        0,
        0,
        0,
        0,
        0,
        0,
        0,
        0,
        0,
        0,
        0,
        0,
        0,
        0,
        0,
        0,
        0,
        0,
        0,
        0,
        0,
        0,
        0,
        0,
        0,
        0,
        0,
        0,
        0,
        0,
        0,
        0,
        0,
        0,
        0,
        0,
        0,
        0,
        0,
        0,
        0,
        0,
        0,
        0,
        0,
        0,
        0,
        0,
        0,
        0,
        0,
        0,
        0,
        0,
        0,
        0,
        0,
        0,
        0,
        0,
        0,
        0,
        0,
        0,
        0,
        0,
        4,
        0,
        0,
        0,
        0,
        0,
        0,
        0,
        0,
        0,
        0,
        0,
        0,
        0,
        0,
        1,
        0,
        0,
        0,
        0,
        0,
        0,
        0,
        0,
        0,
        0,
        0,
        0,
        0,
        0,
        0,
        0,
        0,
        0,
        0,
        0,
        0,
        0,
        0,
        0,
        0,
        0,
        0,
        0,
        0,
        0,
        4,
        0,
        0,
        0,
        0,
        0,
        0,
        0,
        0,
        0,
        0,
        0,
        0,
        0,
        0,
        0,
        0,
        0,
        0,
        0,
        0,
        0,
        0,
        0,
        0,
        0,
        0,
        0,
        0,
        0,
        0,
        0,
        0,
        0,
        0,
        0,
        0,
        0,
        0,
        0,
        0,
        0,
        0,
        0,
        0,
        0,
        0,
        0,
        0,
        0,
        0,
        0,
        0,
        0,
        0,
        0,
        0,
        0,
        0,
        0,
        0,
        0,
        0,
        0,
        0,
        0,
        0,
        0,
        0,
        0,
        0,
        0,
        0,
        0,
        0,
        0,
        0,
        0,
        0,
        0,
        0,
        16,
        0,
        0,
        0,
        0,
        0,
        0,
        0,
        0,
        0,
        0,
        0,
        0,
        0,
        0,
        0,
        0,
        0,
        0,
        0,
        0,
        0,
        0,
        0,
        0,
        0,
        0,
        0,
        0,
        0,
        0,
        0,
        0,
        0,
        0,
        0,
        0,
        0,
        0,
        0,
        0,
        0,
        0,
        0,
        0,
        0,
        0,
        0,
        0,
        0,
        0,
        0,
        0,
        0,
        0,
        0,
        0,
        0,
        0,
        0,
        0,
        0,
        0,
        0,
        0,
        0,
        0,
        0,
        0,
        9,
        0,
        0,
        0,
        0,
        0,
        0,
        0,
        0,
        0
    ],
    "6": [
        1755,
        1695,
        1512,
        1573,
        1742,
        1555,
        1911,
        1354,
        1465,
        1915,
        2123,
        1605,
        1677,
        1956,
        1753,
        1546,
        1686,
        1780,
        1811,
        1484,
        1658,
        1726,
        1867,
        1534,
        1496,
        1391,
        1630,
        1598,
        1681,
        1341,
        2286,
        2045,
        1907,
        2203,
        2008,
        1910,
        1852,
        2337,
        1738,
        1705,
        1652,
        1769,
        1517,
        1543,
        1460,
        1709,
        1492,
        1365,
        1614,
        1448,
        1939,
        1520,
        2008,
        1782,
        1869,
        1835,
        1782,
        1646,
        1987,
        1805,
        1537,
        1635,
        1544,
        1488,
        1381,
        1744,
        1559,
        1383,
        1799,
        1479,
        1845,
        2048,
        1884,
        1593,
        1742,
        2008,
        1637,
        1783,
        1624,
        1610,
        1591,
        1516,
        1730,
        1418,
        1680,
        1765,
        1748,
        1441,
        1731,
        1344,
        1416,
        1494,
        1417,
        1500,
        1265,
        1509,
        1422,
        1345,
        1248,
        1469,
        1400,
        1365,
        1295,
        1547,
        1431,
        1519,
        1345,
        1645,
        1683,
        1261,
        1444,
        1591,
        1378,
        1234,
        1605,
        1345,
        1543,
        1681,
        1510,
        1535,
        1422,
        1485,
        1324,
        1402,
        1217,
        1377,
        1462,
        1617,
        1213,
        1468,
        1611,
        1687,
        1699,
        1777,
        1540,
        1762,
        1481,
        1855,
        1529,
        1786,
        1427,
        1361,
        1133,
        1522,
        1536,
        1314,
        1205,
        1218,
        1311,
        1376,
        1630,
        1641,
        1847,
        1510,
        1519,
        1484,
        1487,
        1966,
        1563,
        1820,
        1726,
        1539,
        1591,
        1695,
        1662,
        1622,
        1397,
        1680,
        1329,
        1486,
        1690,
        1283,
        1374,
        1366,
        985,
        1207,
        1232,
        1258,
        1320,
        1462,
        1502,
        1126,
        1170,
        1330,
        1335,
        1077,
        1261,
        1196,
        1129,
        1174,
        1330,
        1400,
        1609,
        1115,
        1488,
        1360,
        1315,
        1455,
        1263,
        1398,
        1707,
        1618,
        1659,
        1749,
        2005,
        1900,
        1816,
        1552,
        1784,
        1775,
        2005,
        2194,
        1978,
        1771,
        1817,
        1666,
        1740,
        1635,
        1952,
        1946,
        1407,
        1230,
        1351,
        1194,
        1109,
        1430,
        1238,
        1528,
        1309,
        1171,
        1325,
        1508,
        1149,
        1047,
        1035,
        1418,
        1237,
        1275,
        1506,
        1061,
        1631,
        1531,
        1335,
        1305,
        1614,
        1281,
        1151,
        1195,
        1223,
        1391,
        1345,
        1196,
        1644,
        1433,
        1388,
        1361,
        1296,
        1344,
        1306,
        1379,
        1880,
        1749,
        1501,
        1771,
        1731,
        1855,
        1665,
        1629,
        1603,
        1379,
        1940,
        1732,
        1541,
        1820,
        1240,
        1540,
        1801,
        1640,
        1912,
        1441,
        1751,
        1833,
        1562,
        1652,
        2153,
        1922,
        2116,
        1937,
        1822,
        2061,
        1677,
        2045,
        2122,
        1875,
        2008,
        2075,
        1893,
        1924,
        1785,
        1690,
        2001,
        1935,
        2198,
        2161,
        1818,
        1968,
        1826,
        1642,
        1769,
        1680,
        1691,
        1706,
        1612,
        1899,
        1875,
        1796,
        1903,
        1772,
        1791,
        1980,
        1834,
        1599,
        1613,
        1884,
        1888,
        1713,
        1620,
        1920,
        1973,
        1746,
        1623,
        1762,
        1949,
        1792,
        1580,
        1561,
        1909,
        2031,
        1934,
        1734,
        2185,
        1865,
        1951,
        1730,
        2263,
        1891,
        2231,
        1947,
        2005,
        1725,
        1448,
        1528,
        1685,
        1555,
        1712,
        1389,
        1647,
        1360,
        1563,
        1408,
        2334,
        1841,
        2132,
        2299,
        2301,
        2090,
        1841,
        2201,
        2068,
        2359,
        1684,
        1854,
        1859,
        1977,
        2053,
        1922,
        1811,
        1710,
        1947,
        2184,
        1981,
        1692,
        1609,
        1791,
        1521,
        1823,
        1939,
        1478,
        1485,
        1504,
        1806,
        1781,
        1607,
        1682,
        1722,
        1462,
        1762,
        1691,
        1710,
        1465,
        2599,
        2348,
        2550,
        2627,
        2232,
        2246,
        2592,
        2159,
        2433,
        2150,
        1780,
        2112,
        1952,
        2111,
        1780,
        2044,
        1756,
        1716,
        1943,
        2136,
        1497,
        1808,
        1699,
        1537,
        1586,
        1592,
        1769,
        1485,
        1834,
        1684,
        2294,
        2411,
        2141,
        2439,
        2059,
        2114,
        2328,
        2031,
        2406,
        2137,
        1844,
        1742,
        1551,
        1730,
        1527,
        1627,
        1502,
        1728,
        1644,
        1862,
        1872,
        2146,
        1879,
        1959,
        2099,
        2215,
        2350,
        2187,
        2279,
        1830,
        1776,
        1582,
        2026,
        2057,
        2150,
        1823,
        1726,
        1573,
        1917,
        1621,
        1934,
        1753,
        2088,
        2245,
        2249,
        2035,
        2184,
        2199,
        1813,
        1773,
        1685,
        1457,
        1533,
        1759,
        1624,
        1379,
        1686,
        1499,
        1849,
        1604,
        1539,
        1592,
        1685,
        1329,
        1819,
        1407,
        1458,
        1481,
        1614,
        1772,
        1719,
        1609,
        1432,
        1721,
        1637,
        1809,
        1656,
        1427,
        1537,
        1722,
        2397,
        1945,
        2083,
        2249,
        2106,
        1965,
        1904,
        1762,
        1899,
        1840,
        2222,
        2038,
        2286,
        2103,
        1969,
        2186,
        1978,
        2308,
        2460,
        2541,
        1755,
        1839,
        1808,
        1847,
        2282,
        1811,
        2069,
        1967,
        1936,
        2066,
        1481,
        1752,
        1372,
        1761,
        1876,
        1770,
        1654,
        1814,
        1934,
        2045,
        1798,
        2266,
        1642,
        2040,
        1929,
        1730,
        1773,
        1773,
        1851,
        2141,
        1900,
        2323,
        1963,
        1675,
        1961,
        2210,
        2316,
        1928,
        1988,
        2186,
        2287,
        2633,
        2666,
        1843,
        2384,
        2196,
        2072,
        2263,
        2310,
        2119,
        1693,
        1938,
        1872,
        1506,
        1881,
        1927,
        1779,
        1795,
        1814,
        1848,
        1827,
        2081,
        1979,
        1561,
        1729,
        2299,
        2127,
        2054,
        2182,
        1679,
        2216,
        2092,
        1858,
        1940,
        1475,
        1827,
        1820,
        1743,
        1495,
        1618,
        2097,
        1873,
        1969,
        2250,
        1802,
        2374,
        2177,
        1936,
        2201,
        2293,
        1983,
        2130,
        2295,
        2420,
        2376,
        2321,
        1957,
        2176,
        1829,
        2053,
        1903,
        2088,
        1872,
        1898,
        1951,
        1801,
        2093,
        1706,
        2149,
        1638,
        2248,
        2131,
        2502,
        2576,
        2385,
        2520,
        2219,
        2422,
        1895,
        2242,
        1880,
        2058,
        1843,
        1720,
        1933,
        1742,
        1925,
        1785,
        2054,
        1653,
        2035,
        1611,
        1592,
        1796,
        1777,
        1906,
        1612,
        1670,
        1644,
        1950,
        2228,
        1704,
        1710,
        1783,
        1937,
        1622,
        1689,
        2128,
        1822,
        1748,
        2119,
        1570,
        2240,
        1680,
        2043,
        1864,
        1814,
        1851,
        2135,
        1662,
        2140,
        2027,
        2162,
        1817,
        2087,
        2302,
        1789,
        2283,
        1931,
        1813,
        1713,
        1901,
        2141,
        1947,
        1645,
        1639,
        1803,
        1920,
        2035,
        1996,
        2119,
        1973,
        1540,
        1655,
        1997,
        1810,
        1962,
        1724,
        1813,
        1639,
        1905,
        1942,
        2039,
        1848,
        2240,
        1925,
        2007,
        1940,
        2179,
        2308,
        2047,
        1832,
        2218,
        1558,
        1761,
        1910,
        1697,
        1908,
        1602,
        2205,
        1867,
        1953,
        1951,
        1823,
        1860,
        1963,
        2131,
        2209,
        2177,
        2096,
        1874,
        2123,
        2180,
        1771,
        1913,
        1664,
        1831,
        1984,
        1543,
        1750,
        2131,
        2499,
        2340,
        2330,
        2385,
        2569,
        2462,
        2070,
        2164,
        2088,
        2170,
        2100,
        1866,
        1733,
        1848,
        2293,
        2005,
        1907,
        2214,
        2130,
        2056,
        1653,
        2231,
        2063,
        1980,
        2229,
        1892,
        1763,
        2093,
        1734,
        2265,
        2077,
        1890,
        1699,
        1809,
        2025,
        1740,
        2154,
        2155,
        2097,
        1645,
        1671,
        1695,
        1862,
        1681,
        1896,
        1579,
        1758,
        1995,
        1884,
        2001,
        1889,
        2335,
        2131,
        2072,
        2335,
        2346,
        2131,
        2030,
        2317,
        2029,
        2187,
        2231,
        2162,
        2043,
        2295,
        1849,
        2282,
        2416,
        1912,
        2214,
        1655,
        1713,
        1913,
        2109,
        1853,
        1941,
        1723,
        1665,
        1864,
        2069,
        2000,
        2314,
        2097,
        2199,
        1967,
        1827,
        2230,
        1839,
        2336,
        1992,
        1784,
        2226,
        1896,
        1716,
        2202,
        2186,
        2248,
        2021,
        2046,
        2562,
        2216,
        2454,
        2150,
        1972,
        2133,
        2001,
        2344,
        2249,
        1985,
        2179,
        2213,
        2335,
        2353,
        2522,
        2363,
        2344,
        2262,
        2070,
        2162,
        1997,
        1790,
        1923,
        2274,
        1861,
        2126,
        1738,
        1595,
        2065,
        2245,
        2043,
        2141,
        1989,
        1652,
        1669,
        1925,
        1744,
        2117,
        1728,
        1864,
        1951,
        2133,
        2116,
        2332,
        1864,
        2195,
        1997,
        2076,
        1756,
        1799,
        2023,
        1702,
        2180,
        2025,
        1927,
        1890,
        1826,
        2066,
        1636,
        2036,
        1961,
        1860,
        2312,
        1792,
        2208,
        1712,
        2284,
        2036,
        2191,
        2055,
        2164,
        2396,
        2394,
        2618,
        2282,
        2211,
        2555,
        2714,
        2279,
        2711,
        2082,
        1620,
        2016,
        1774,
        2146,
        1764,
        1864,
        1791,
        1688,
        2112,
        2166,
        1932,
        2299,
        2166,
        2433,
        2130,
        1951,
        2224,
        2368,
        2522,
        1992,
        1948,
        2005,
        2142,
        1946,
        2175,
        2060,
        2381,
        2391,
        2008,
        2511,
        2261,
        2258,
        2316,
        2491,
        2087,
        2602,
        2539,
        2165,
        2023,
        2374,
        2525,
        2254,
        2436,
        2334,
        2214,
        2481,
        1905,
        1935,
        2013,
        2066,
        1767,
        2200,
        1780,
        2256,
        2090,
        2019,
        1653,
        2314,
        1681,
        2010,
        1863,
        2170,
        1917,
        1852,
        2064,
        2274,
        1776,
        2425,
        2416
    ],
    "TOT_WITNESS": 4,
    "TOT_WATCHERS": 10,
    "TOT_USER_INSTANCES": 100,
    "TOT_USERS_PER_USER_INSTANCE": 10,
    "WITNESS_HW": "c5a.2xlarge",
    "WATCHER_HW": "c5a.2xlarge",
    "USER_HW": "t3.micro",
    "USER_WITNESSES": 3,
    "USER_WITNESSES_THREESHOLD": 3,
    "USER_WATCHERS": 7,
    "ISSUER_WITNESSES": 4,
    "ISSUER_WITNESSES_THREESHOLD": 4,
    "ISSUER_WATCHERS": 10
}